jk_systools/AbstractCLICmd.py
jk_systools/AbstractMultiCmdCLIApp.py
jk_systools/AppColors.py
jk_systools/AppRuntime.py
jk_systools/CLIRunCtx.py
jk_systools/IExitCodes.py
jk_systools/__init__.py
jk_systools/bin/_DataCtx.py
jk_systools/bin/cli_df.py
jk_systools/bin/cli_mount.py
jk_systools-0.2025.8.24.dist-info/entry_points.txt
jk_systools-0.2025.8.24.dist-info/licenses/LICENSE.txt
jk_systools-0.2025.8.24.dist-info/WHEEL
jk_systools-0.2025.8.24.dist-info/METADATA
jk_systools-0.2025.8.24.dist-info/RECORD
