Metadata-Version: 2.4
Name: jk_systools
Version: 0.2025.8.24
Summary: This python tool provides alternatives and additions to classic Linux system tools.
Keywords: console,terminal,cli
Author-email: Jürgen Knauth <pubsrc@binary-overflow.de>
Maintainer-email: Jürgen Knauth <pubsrc@binary-overflow.de>
Requires-Python: >=3.8
Classifier: Development Status :: 5 - Production/Stable
Classifier: License :: OSI Approved :: Apache Software License
Classifier: Programming Language :: Python :: 3
License-File: LICENSE.txt
Requires-Dist: tqdm >= 4.67.1
Requires-Dist: jk_dirwalker >= 0.2025.2.15
Requires-Dist: jk_argparsing >= 0.2024.12.23
Requires-Dist: jk_typing >= 0.2025.2.1
Requires-Dist: jk_logging >= 0.2025.1.26
Requires-Dist: jk_console >= 0.2025.2.23.1
Requires-Dist: jk_mounting >= 0.2025.7.11
Requires-Dist: jk_sysinfo >= 0.2024.9.18.3
Requires-Dist: jk_flexdata >= 0.2025.3.2
